Helpers/__init__.py
Helpers/download_models.py
Helpers/utils.py
TF2/__init__.py
TF2/detect.py
TF2/setup.py
TF2/object_detection/__init__.py
TF2/object_detection/eval_util.py
TF2/object_detection/eval_util_test.py
TF2/object_detection/export_inference_graph.py
TF2/object_detection/export_tflite_graph_lib_tf2.py
TF2/object_detection/export_tflite_graph_lib_tf2_test.py
TF2/object_detection/export_tflite_graph_tf2.py
TF2/object_detection/export_tflite_ssd_graph.py
TF2/object_detection/export_tflite_ssd_graph_lib.py
TF2/object_detection/export_tflite_ssd_graph_lib_tf1_test.py
TF2/object_detection/exporter.py
TF2/object_detection/exporter_lib_tf2_test.py
TF2/object_detection/exporter_lib_v2.py
TF2/object_detection/exporter_main_v2.py
TF2/object_detection/exporter_tf1_test.py
TF2/object_detection/inputs.py
TF2/object_detection/inputs_test.py
TF2/object_detection/model_hparams.py
TF2/object_detection/model_lib.py
TF2/object_detection/model_lib_tf1_test.py
TF2/object_detection/model_lib_tf2_test.py
TF2/object_detection/model_lib_v2.py
TF2/object_detection/model_main.py
TF2/object_detection/model_main_tf2.py
TF2/object_detection/model_tpu_main.py
TF2/object_detection/anchor_generators/__init__.py
TF2/object_detection/anchor_generators/flexible_grid_anchor_generator.py
TF2/object_detection/anchor_generators/flexible_grid_anchor_generator_test.py
TF2/object_detection/anchor_generators/grid_anchor_generator.py
TF2/object_detection/anchor_generators/grid_anchor_generator_test.py
TF2/object_detection/anchor_generators/multiple_grid_anchor_generator.py
TF2/object_detection/anchor_generators/multiple_grid_anchor_generator_test.py
TF2/object_detection/anchor_generators/multiscale_grid_anchor_generator.py
TF2/object_detection/anchor_generators/multiscale_grid_anchor_generator_test.py
TF2/object_detection/box_coders/__init__.py
TF2/object_detection/box_coders/faster_rcnn_box_coder.py
TF2/object_detection/box_coders/faster_rcnn_box_coder_test.py
odcommonapp-0.0.5.dist-info/METADATA
odcommonapp-0.0.5.dist-info/WHEEL
odcommonapp-0.0.5.dist-info/top_level.txt
odcommonapp-0.0.5.dist-info/RECORD
