Metadata-Version: 2.1
Name: odcommonapp
Version: 0.0.5
Summary: Object detection common framework application
Home-page: https://github.com/thangarajdeivasikamani/odcommonapp
Author: thangarajdeivasikamani
Author-email: Thangarajerode@gmail.com
License: UNKNOWN
Project-URL: Bug Tracker, https://github.com/thangarajdeivasikamani/odcommonapp/issues
Platform: UNKNOWN
Classifier: Programming Language :: Python :: 3
Classifier: License :: OSI Approved :: MIT License
Classifier: Operating System :: OS Independent
Requires-Python: >=3.8
Requires-Dist: Cython (==0.29.28)
Requires-Dist: Flask (==2.0.3)
Requires-Dist: Flask-Cors (==3.0.10)
Requires-Dist: Keras-Preprocessing (==1.1.2)
Requires-Dist: matplotlib (==3.3.4)
Requires-Dist: numpy (==1.19.5)
Requires-Dist: opencv-python (==4.5.5.64)
Requires-Dist: Pillow (==8.4.0)
Requires-Dist: proto-plus (==1.20.3)
Requires-Dist: protobuf (==3.19.4)
Requires-Dist: pyarrow (==6.0.1)
Requires-Dist: tensorflow (==2.5.0)
Requires-Dist: tensorflow-estimator (==2.5.0)
Requires-Dist: termcolor (==1.1.0)
Requires-Dist: zipp (==3.6.0)
Requires-Dist: wget (==3.2)
Requires-Dist: torch (==1.10.1)
Requires-Dist: torchvision (==0.11.2)
Requires-Dist: torchaudio (==0.10.1)
Requires-Dist: cloudpickle
Requires-Dist: omegaconf
Requires-Dist: pycocotools-windows
Requires-Dist: fvcore
Requires-Dist: seaborn (>=0.11.0)
Requires-Dist: youtube-dl
